booking/__init__.py
booking/admin.py
booking/apps.py
booking/forms.py
booking/models.py
booking/tests.py
booking/urls.py
booking/views.py
booking/migrations/0001_initial.py
booking/migrations/0002_bookingmanager.py
booking/migrations/__init__.py
booking/templates/booking/base.html
booking/templates/booking/side_nav.html
booking/templates/booking/admin/appointment_list.html
booking/templates/booking/admin/appointment_settings.html
booking/templates/booking/admin/dashboard.html
booking/templates/booking/admin/components/appointment_tabel.html
booking/templates/booking/admin/components/home_top_card.html
booking/templates/booking/admin/components/show_errors.html
booking/templates/booking/user/base.html
booking/templates/booking/user/create_booking.html
dj_booking-1.1.dist-info/LICENSE
dj_booking-1.1.dist-info/METADATA
dj_booking-1.1.dist-info/WHEEL
dj_booking-1.1.dist-info/top_level.txt
dj_booking-1.1.dist-info/RECORD
