Metadata-Version: 2.1
Name: dj-booking
Version: 1.1
Summary: Django Booking is a complete Django booking system as a package.
Home-page: https://github.com/foad-heidari/dj-booking
Author: Foad
Author-email: foad.haydri.1377@gmail.com
Maintainer: Foad
Maintainer-email: foad.haydri.1377@gmail.com
License: MIT
Keywords: django booking appointment appointment-booking booking-system appointment-system doctor-appointment-booking
Platform: UNKNOWN
Classifier: Environment :: Web Environment
Classifier: Framework :: Django
Classifier: Framework :: Django :: 1.11
Classifier: Intended Audience :: Developers
Classifier: License :: OSI Approved :: MIT License
Classifier: Operating System :: OS Independent
Classifier: Programming Language :: Python
Classifier: Programming Language :: Python :: 3
Classifier: Programming Language :: Python :: 3 :: Only
Classifier: Programming Language :: Python :: 3.5
Classifier: Programming Language :: Python :: 3.6
Classifier: Programming Language :: Python :: 3.7
Classifier: Programming Language :: Python :: 3.8
Classifier: Topic :: Internet :: WWW/HTTP
Classifier: Topic :: Internet :: WWW/HTTP :: Dynamic Content
Classifier: Topic :: Software Development :: Libraries :: Python Modules
License-File: LICENSE
